{
"meta":{"test_sets":[],"test_metrics":[],"learn_metrics":[{"best_value":"Min","name":"MultiClass"}],"launch_mode":"Train","parameters":"","iteration_count":422,"learn_sets":["learn"],"name":"experiment"},
"iterations":[
{"learn":[0.8737860838],"iteration":0,"passed_time":0.009421005389,"remaining_time":3.966243269},
{"learn":[0.7206836093],"iteration":1,"passed_time":0.01808963955,"remaining_time":3.798824305},
{"learn":[0.6164561738],"iteration":2,"passed_time":0.0261829869,"remaining_time":3.656890504},
{"learn":[0.5421266246],"iteration":3,"passed_time":0.03517880162,"remaining_time":3.676184769},
{"learn":[0.4838543015],"iteration":4,"passed_time":0.0439529182,"remaining_time":3.665673378},
{"learn":[0.4285005587],"iteration":5,"passed_time":0.05251352916,"remaining_time":3.640938022},
{"learn":[0.3838067632],"iteration":6,"passed_time":0.06145320662,"remaining_time":3.64329725},
{"learn":[0.3556440461],"iteration":7,"passed_time":0.07003196316,"remaining_time":3.624154093},
{"learn":[0.3258767189],"iteration":8,"passed_time":0.07917980459,"remaining_time":3.633473255},
{"learn":[0.2987136887],"iteration":9,"passed_time":0.08768313795,"remaining_time":3.612545284},
{"learn":[0.2742240726],"iteration":10,"passed_time":0.09640498847,"remaining_time":3.602040933},
{"learn":[0.2569428761],"iteration":11,"passed_time":0.1048573562,"remaining_time":3.582626335},
{"learn":[0.2418215471],"iteration":12,"passed_time":0.1132137944,"remaining_time":3.561880146},
{"learn":[0.2298265623],"iteration":13,"passed_time":0.122118211,"remaining_time":3.558873578},
{"learn":[0.2193859172],"iteration":14,"passed_time":0.1307716305,"remaining_time":3.54827024},
{"learn":[0.2099544331],"iteration":15,"passed_time":0.1396401161,"remaining_time":3.543367945},
{"learn":[0.2018485161],"iteration":16,"passed_time":0.1485480438,"remaining_time":3.53893869},
{"learn":[0.1951438145],"iteration":17,"passed_time":0.1574839901,"remaining_time":3.534640666},
{"learn":[0.1889920129],"iteration":18,"passed_time":0.1664988707,"remaining_time":3.531528678},
{"learn":[0.1817764657],"iteration":19,"passed_time":0.1752651448,"remaining_time":3.522829411},
{"learn":[0.1767043619],"iteration":20,"passed_time":0.1841043514,"remaining_time":3.515516424},
{"learn":[0.1713038706],"iteration":21,"passed_time":0.1924886782,"remaining_time":3.499794149},
{"learn":[0.1677624684],"iteration":22,"passed_time":0.2009259112,"remaining_time":3.485627764},
{"learn":[0.1629238611],"iteration":23,"passed_time":0.2095203726,"remaining_time":3.474546179},
{"learn":[0.158480983],"iteration":24,"passed_time":0.2182308796,"remaining_time":3.465506368},
{"learn":[0.1528854321],"iteration":25,"passed_time":0.2272546429,"remaining_time":3.461263023},
{"learn":[0.1504720233],"iteration":26,"passed_time":0.2367197319,"remaining_time":3.463122003},
{"learn":[0.1473833391],"iteration":27,"passed_time":0.2465017082,"remaining_time":3.46863118},
{"learn":[0.1430669193],"iteration":28,"passed_time":0.2557135193,"remaining_time":3.465359072},
{"learn":[0.1404844669],"iteration":29,"passed_time":0.2650046348,"remaining_time":3.462727228},
{"learn":[0.1367894526],"iteration":30,"passed_time":0.274308164,"remaining_time":3.459822327},
{"learn":[0.1348810016],"iteration":31,"passed_time":0.2835019496,"remaining_time":3.455180011},
{"learn":[0.1318936553],"iteration":32,"passed_time":0.2926244232,"remaining_time":3.449421232},
{"learn":[0.1305997386],"iteration":33,"passed_time":0.301512935,"remaining_time":3.44079467},
{"learn":[0.1278560206],"iteration":34,"passed_time":0.3109950992,"remaining_time":3.438717239},
{"learn":[0.1257319263],"iteration":35,"passed_time":0.3199683469,"remaining_time":3.43077172},
{"learn":[0.1231156625],"iteration":36,"passed_time":0.3289310336,"remaining_time":3.422660755},
{"learn":[0.1210714155],"iteration":37,"passed_time":0.3379732504,"remaining_time":3.415308636},
{"learn":[0.118726051],"iteration":38,"passed_time":0.3469954533,"remaining_time":3.407673297},
{"learn":[0.1170991216],"iteration":39,"passed_time":0.3564651736,"remaining_time":3.404242408},
{"learn":[0.1146141667],"iteration":40,"passed_time":0.3659760266,"remaining_time":3.400899174},
{"learn":[0.1121047989],"iteration":41,"passed_time":0.3753711241,"remaining_time":3.396214932},
{"learn":[0.1100133053],"iteration":42,"passed_time":0.3850084859,"remaining_time":3.393446888},
{"learn":[0.1077797557],"iteration":43,"passed_time":0.3939666691,"remaining_time":3.384531839},
{"learn":[0.1067204171],"iteration":44,"passed_time":0.4027660934,"remaining_time":3.374284827},
{"learn":[0.1046821912],"iteration":45,"passed_time":0.4113629355,"remaining_time":3.362444864},
{"learn":[0.1034036998],"iteration":46,"passed_time":0.4205513695,"remaining_time":3.355463054},
{"learn":[0.1019705814],"iteration":47,"passed_time":0.4293246058,"remaining_time":3.34515422},
{"learn":[0.1015974819],"iteration":48,"passed_time":0.4383642539,"remaining_time":3.336936056},
{"learn":[0.09886796166],"iteration":49,"passed_time":0.4472001095,"remaining_time":3.327168815},
{"learn":[0.09652347404],"iteration":50,"passed_time":0.4568938187,"remaining_time":3.323678563},
{"learn":[0.09514935423],"iteration":51,"passed_time":0.4662296979,"remaining_time":3.31740362},
{"learn":[0.09444664432],"iteration":52,"passed_time":0.47485913,"remaining_time":3.306094698},
{"learn":[0.09197857312],"iteration":53,"passed_time":0.4840937081,"remaining_time":3.299008974},
{"learn":[0.09087390326],"iteration":54,"passed_time":0.4934717803,"remaining_time":3.292802607},
{"learn":[0.08915077086],"iteration":55,"passed_time":0.5023768271,"remaining_time":3.283391406},
{"learn":[0.08751767608],"iteration":56,"passed_time":0.5116309612,"remaining_time":3.276233348},
{"learn":[0.086347443],"iteration":57,"passed_time":0.5205480118,"remaining_time":3.266887522},
{"learn":[0.0855392448],"iteration":58,"passed_time":0.5295373145,"remaining_time":3.258000765},
{"learn":[0.08474561113],"iteration":59,"passed_time":0.5396961566,"remaining_time":3.256166812},
{"learn":[0.08414014397],"iteration":60,"passed_time":0.5488414373,"remaining_time":3.248061621},
{"learn":[0.08324506008],"iteration":61,"passed_time":0.5579913193,"remaining_time":3.239949596},
{"learn":[0.08195621851],"iteration":62,"passed_time":0.5680089481,"remaining_time":3.236749403},
{"learn":[0.08103375965],"iteration":63,"passed_time":0.5800676841,"remaining_time":3.244753608},
{"learn":[0.07985909885],"iteration":64,"passed_time":0.5891024708,"remaining_time":3.235532032},
{"learn":[0.07909803899],"iteration":65,"passed_time":0.5982880439,"remaining_time":3.227129449},
{"learn":[0.07800304765],"iteration":66,"passed_time":0.6074215209,"remaining_time":3.218427461},
{"learn":[0.07692380523],"iteration":67,"passed_time":0.6163319594,"remaining_time":3.208551671},
{"learn":[0.07623337472],"iteration":68,"passed_time":0.6250712652,"remaining_time":3.197828357},
{"learn":[0.07479759394],"iteration":69,"passed_time":0.6339461728,"remaining_time":3.187843612},
{"learn":[0.07422058881],"iteration":70,"passed_time":0.6427699446,"remaining_time":3.177637332},
{"learn":[0.07374653554],"iteration":71,"passed_time":0.6515252254,"remaining_time":3.167136512},
{"learn":[0.0724721538],"iteration":72,"passed_time":0.660527082,"remaining_time":3.157862351},
{"learn":[0.07116491574],"iteration":73,"passed_time":0.6700523694,"remaining_time":3.151057089},
{"learn":[0.06981978441],"iteration":74,"passed_time":0.6796758971,"remaining_time":3.144633817},
{"learn":[0.06882109932],"iteration":75,"passed_time":0.6888511622,"remaining_time":3.136085554},
{"learn":[0.06737827011],"iteration":76,"passed_time":0.7008070514,"remaining_time":3.139979646},
{"learn":[0.0668444978],"iteration":77,"passed_time":0.7099171112,"remaining_time":3.13091649},
{"learn":[0.06602536962],"iteration":78,"passed_time":0.7188431345,"remaining_time":3.121053103},
{"learn":[0.06477978591],"iteration":79,"passed_time":0.7280191345,"remaining_time":3.1122818},
{"learn":[0.0641101259],"iteration":80,"passed_time":0.7369670745,"remaining_time":3.1025404},
{"learn":[0.06304990899],"iteration":81,"passed_time":0.7456629371,"remaining_time":3.091773154},
{"learn":[0.06228989599],"iteration":82,"passed_time":0.754828704,"remaining_time":3.082975068},
{"learn":[0.06137724409],"iteration":83,"passed_time":0.76376356,"remaining_time":3.073239087},
{"learn":[0.06070076201],"iteration":84,"passed_time":0.7730828341,"remaining_time":3.06504606},
{"learn":[0.06033001934],"iteration":85,"passed_time":0.7822690173,"remaining_time":3.056306858},
{"learn":[0.05968975734],"iteration":86,"passed_time":0.7917581037,"remaining_time":3.048723732},
{"learn":[0.05879287325],"iteration":87,"passed_time":0.8018162048,"remaining_time":3.043256959},
{"learn":[0.05782271058],"iteration":88,"passed_time":0.8110507929,"remaining_time":3.034605776},
{"learn":[0.05747389804],"iteration":89,"passed_time":0.8209694413,"remaining_time":3.02846505},
{"learn":[0.05682424463],"iteration":90,"passed_time":0.8307452357,"remaining_time":3.021721682},
{"learn":[0.05579550791],"iteration":91,"passed_time":0.840143324,"remaining_time":3.013557575},
{"learn":[0.05551382368],"iteration":92,"passed_time":0.849732071,"remaining_time":3.006041412},
{"learn":[0.05471145534],"iteration":93,"passed_time":0.8593668421,"remaining_time":2.998641747},
{"learn":[0.05388364261],"iteration":94,"passed_time":0.8694290145,"remaining_time":2.992666187},
{"learn":[0.05327453281],"iteration":95,"passed_time":0.8791583147,"remaining_time":2.98547511},
{"learn":[0.05270561061],"iteration":96,"passed_time":0.8885299949,"remaining_time":2.977033488},
{"learn":[0.05186601867],"iteration":97,"passed_time":0.8978228509,"remaining_time":2.968312283},
{"learn":[0.05149948685],"iteration":98,"passed_time":0.9074360954,"remaining_time":2.960624836},
{"learn":[0.05097751493],"iteration":99,"passed_time":0.91682206,"remaining_time":2.952167033},
{"learn":[0.05066967259],"iteration":100,"passed_time":0.9260641004,"remaining_time":2.943233428},
{"learn":[0.0499507043],"iteration":101,"passed_time":0.9349382777,"remaining_time":2.933139695},
{"learn":[0.04944010687],"iteration":102,"passed_time":0.943851447,"remaining_time":2.923190404},
{"learn":[0.04890763455],"iteration":103,"passed_time":0.9518507155,"remaining_time":2.910466611},
{"learn":[0.0480846644],"iteration":104,"passed_time":0.960409856,"remaining_time":2.899523089},
{"learn":[0.04748823571],"iteration":105,"passed_time":0.969123794,"remaining_time":2.889086028},
{"learn":[0.04676367301],"iteration":106,"passed_time":0.977915396,"remaining_time":2.878909811},
{"learn":[0.04635951577],"iteration":107,"passed_time":0.9869237246,"remaining_time":2.869389347},
{"learn":[0.04581536594],"iteration":108,"passed_time":0.995817798,"remaining_time":2.859550191},
{"learn":[0.04545535382],"iteration":109,"passed_time":1.00477106,"remaining_time":2.849896096},
{"learn":[0.04529035122],"iteration":110,"passed_time":1.014168488,"remaining_time":2.841499096},
{"learn":[0.04494334043],"iteration":111,"passed_time":1.02328778,"remaining_time":2.832314392},
{"learn":[0.04448970156],"iteration":112,"passed_time":1.031570346,"remaining_time":2.820842804},
{"learn":[0.04400151492],"iteration":113,"passed_time":1.03974991,"remaining_time":2.809148879},
{"learn":[0.0435186576],"iteration":114,"passed_time":1.047974878,"remaining_time":2.797637282},
{"learn":[0.04323292448],"iteration":115,"passed_time":1.056285812,"remaining_time":2.786409124},
{"learn":[0.04291297951],"iteration":116,"passed_time":1.064615772,"remaining_time":2.775280431},
{"learn":[0.04238597219],"iteration":117,"passed_time":1.073412095,"remaining_time":2.765400652},
{"learn":[0.0421050563],"iteration":118,"passed_time":1.082095939,"remaining_time":2.755252686},
{"learn":[0.04174248148],"iteration":119,"passed_time":1.094028907,"remaining_time":2.753306082},
{"learn":[0.04136297253],"iteration":120,"passed_time":1.102799572,"remaining_time":2.743327862},
{"learn":[0.04091589561],"iteration":121,"passed_time":1.111498566,"remaining_time":2.733193195},
{"learn":[0.04065884996],"iteration":122,"passed_time":1.119958026,"remaining_time":2.722499591},
{"learn":[0.04041297638],"iteration":123,"passed_time":1.128898884,"remaining_time":2.71299893},
{"learn":[0.03994870489],"iteration":124,"passed_time":1.13776988,"remaining_time":2.703341235},
{"learn":[0.03944437553],"iteration":125,"passed_time":1.146617159,"remaining_time":2.69364031},
{"learn":[0.03902357673],"iteration":126,"passed_time":1.155185382,"remaining_time":2.683304628},
{"learn":[0.0386245413],"iteration":127,"passed_time":1.163457465,"remaining_time":2.672316364},
{"learn":[0.0383765748],"iteration":128,"passed_time":1.172165331,"remaining_time":2.662360015},
{"learn":[0.03793152886],"iteration":129,"passed_time":1.180973958,"remaining_time":2.652649198},
{"learn":[0.03768961742],"iteration":130,"passed_time":1.189935942,"remaining_time":2.643292818},
{"learn":[0.03734432645],"iteration":131,"passed_time":1.199302401,"remaining_time":2.634831032},
{"learn":[0.0368236089],"iteration":132,"passed_time":1.208695818,"remaining_time":2.626414221},
{"learn":[0.03647225145],"iteration":133,"passed_time":1.217851662,"remaining_time":2.617472228},
{"learn":[0.03635746591],"iteration":134,"passed_time":1.228622482,"remaining_time":2.611960387},
{"learn":[0.03611780755],"iteration":135,"passed_time":1.23837705,"remaining_time":2.60423409},
{"learn":[0.0357756111],"iteration":136,"passed_time":1.247563573,"remaining_time":2.595296484},
{"learn":[0.03558473553],"iteration":137,"passed_time":1.256698221,"remaining_time":2.586248512},
{"learn":[0.03542685739],"iteration":138,"passed_time":1.2653195,"remaining_time":2.57615409},
{"learn":[0.03516356964],"iteration":139,"passed_time":1.274352136,"remaining_time":2.566909303},
{"learn":[0.03480295308],"iteration":140,"passed_time":1.2830535,"remaining_time":2.557007331},
{"learn":[0.03436400437],"iteration":141,"passed_time":1.29200004,"remaining_time":2.547605713},
{"learn":[0.03413941842],"iteration":142,"passed_time":1.3016962,"remaining_time":2.539673005},
{"learn":[0.03367641472],"iteration":143,"passed_time":1.310850343,"remaining_time":2.530669413},
{"learn":[0.03342190486],"iteration":144,"passed_time":1.320232347,"remaining_time":2.522099035},
{"learn":[0.03309972445],"iteration":145,"passed_time":1.329896707,"remaining_time":2.514051309},
{"learn":[0.03288379912],"iteration":146,"passed_time":1.339672091,"remaining_time":2.506189286},
{"learn":[0.03261903304],"iteration":147,"passed_time":1.349375723,"remaining_time":2.498168569},
{"learn":[0.03237911891],"iteration":148,"passed_time":1.358772581,"remaining_time":2.489563186},
{"learn":[0.03204776042],"iteration":149,"passed_time":1.368149593,"remaining_time":2.480911262},
{"learn":[0.03181328101],"iteration":150,"passed_time":1.377131884,"remaining_time":2.471541328},
{"learn":[0.03151239756],"iteration":151,"passed_time":1.386681499,"remaining_time":2.463184241},
{"learn":[0.03137602685],"iteration":152,"passed_time":1.395973514,"remaining_time":2.454358663},
{"learn":[0.03097131898],"iteration":153,"passed_time":1.405176883,"remaining_time":2.445372757},
{"learn":[0.03068333205],"iteration":154,"passed_time":1.414782245,"remaining_time":2.437076512},
{"learn":[0.03031334844],"iteration":155,"passed_time":1.42413845,"remaining_time":2.42833864},
{"learn":[0.03007202626],"iteration":156,"passed_time":1.433192573,"remaining_time":2.419083006},
{"learn":[0.02990763821],"iteration":157,"passed_time":1.442641407,"remaining_time":2.41048944},
{"learn":[0.02961925689],"iteration":158,"passed_time":1.451882457,"remaining_time":2.401541423},
{"learn":[0.02931453389],"iteration":159,"passed_time":1.461004901,"remaining_time":2.392395525},
{"learn":[0.02908569798],"iteration":160,"passed_time":1.470040898,"remaining_time":2.383109778},
{"learn":[0.02898806822],"iteration":161,"passed_time":1.478878984,"remaining_time":2.373509481},
{"learn":[0.02862284437],"iteration":162,"passed_time":1.487630344,"remaining_time":2.36378073},
{"learn":[0.02839982851],"iteration":163,"passed_time":1.496996232,"remaining_time":2.355030658},
{"learn":[0.02834426344],"iteration":164,"passed_time":1.506769756,"remaining_time":2.346908044},
{"learn":[0.02819111858],"iteration":165,"passed_time":1.515814526,"remaining_time":2.337641678},
{"learn":[0.0279232058],"iteration":166,"passed_time":1.525429271,"remaining_time":2.329248287},
{"learn":[0.02769150829],"iteration":167,"passed_time":1.534858799,"remaining_time":2.320560326},
{"learn":[0.02757758132],"iteration":168,"passed_time":1.544660351,"remaining_time":2.312420525},
{"learn":[0.02746142546],"iteration":169,"passed_time":1.554707481,"remaining_time":2.304625207},
{"learn":[0.02737403778],"iteration":170,"passed_time":1.563668393,"remaining_time":2.295209161},
{"learn":[0.02719401551],"iteration":171,"passed_time":1.572650583,"remaining_time":2.285829336},
{"learn":[0.02695093757],"iteration":172,"passed_time":1.581969377,"remaining_time":2.276938583},
{"learn":[0.02678745215],"iteration":173,"passed_time":1.591297194,"remaining_time":2.268055771},
{"learn":[0.02659798531],"iteration":174,"passed_time":1.600272132,"remaining_time":2.258669809},
{"learn":[0.02635380868],"iteration":175,"passed_time":1.611168121,"remaining_time":2.251973624},
{"learn":[0.02617939417],"iteration":176,"passed_time":1.621825846,"remaining_time":2.244900183},
{"learn":[0.0260212094],"iteration":177,"passed_time":1.633134852,"remaining_time":2.238679235},
{"learn":[0.02586687672],"iteration":178,"passed_time":1.643432352,"remaining_time":2.231028277},
{"learn":[0.02564155854],"iteration":179,"passed_time":1.653708335,"remaining_time":2.223318984},
{"learn":[0.02545869487],"iteration":180,"passed_time":1.663834937,"remaining_time":2.21538243},
{"learn":[0.02534296145],"iteration":181,"passed_time":1.673968422,"remaining_time":2.207430886},
{"learn":[0.0251905597],"iteration":182,"passed_time":1.68383641,"remaining_time":2.199108753},
{"learn":[0.02497206292],"iteration":183,"passed_time":1.693320679,"remaining_time":2.190273487},
{"learn":[0.02465709953],"iteration":184,"passed_time":1.702867063,"remaining_time":2.181510778},
{"learn":[0.02444510316],"iteration":185,"passed_time":1.713441043,"remaining_time":2.174043474},
{"learn":[0.0242794825],"iteration":186,"passed_time":1.72558523,"remaining_time":2.168516198},
{"learn":[0.0241498515],"iteration":187,"passed_time":1.735828328,"remaining_time":2.16055228},
{"learn":[0.02394156586],"iteration":188,"passed_time":1.746306988,"remaining_time":2.152854647},
{"learn":[0.02380836617],"iteration":189,"passed_time":1.756599672,"remaining_time":2.144900652},
{"learn":[0.02370431993],"iteration":190,"passed_time":1.766576428,"remaining_time":2.136540078},
{"learn":[0.02350858423],"iteration":191,"passed_time":1.777623893,"remaining_time":2.129445289},
{"learn":[0.02340111745],"iteration":192,"passed_time":1.788464835,"remaining_time":2.122064493},
{"learn":[0.02325467887],"iteration":193,"passed_time":1.799916054,"remaining_time":2.11536526},
{"learn":[0.02309829535],"iteration":194,"passed_time":1.810860588,"remaining_time":2.108027453},
{"learn":[0.02290915526],"iteration":195,"passed_time":1.821437198,"remaining_time":2.100228606},
{"learn":[0.02271646208],"iteration":196,"passed_time":1.831337171,"remaining_time":2.091628749},
{"learn":[0.0225945939],"iteration":197,"passed_time":1.841929756,"remaining_time":2.08379932},
{"learn":[0.02242581895],"iteration":198,"passed_time":1.852346008,"remaining_time":2.075744521},
{"learn":[0.02227931458],"iteration":199,"passed_time":1.862980756,"remaining_time":2.067908639},
{"learn":[0.02212593607],"iteration":200,"passed_time":1.873010359,"remaining_time":2.059379548},
{"learn":[0.02202735981],"iteration":201,"passed_time":1.883185586,"remaining_time":2.050994202},
{"learn":[0.02192599434],"iteration":202,"passed_time":1.892713644,"remaining_time":2.041893045},
{"learn":[0.02177288348],"iteration":203,"passed_time":1.902622419,"remaining_time":2.033194546},
{"learn":[0.02161055733],"iteration":204,"passed_time":1.912505607,"remaining_time":2.024457154},
{"learn":[0.02147883415],"iteration":205,"passed_time":1.922075448,"remaining_time":2.015380081},
{"learn":[0.02138279025],"iteration":206,"passed_time":1.93168266,"remaining_time":2.006337063},
{"learn":[0.02127449489],"iteration":207,"passed_time":1.942396443,"remaining_time":1.99842711},
{"learn":[0.02115517237],"iteration":208,"passed_time":1.951898153,"remaining_time":1.989255056},
{"learn":[0.02096885943],"iteration":209,"passed_time":1.960992228,"remaining_time":1.979668345},
{"learn":[0.02081885333],"iteration":210,"passed_time":1.970217964,"remaining_time":1.970217964},
{"learn":[0.02074570542],"iteration":211,"passed_time":1.979343538,"remaining_time":1.960670486},
{"learn":[0.0206899988],"iteration":212,"passed_time":1.988351987,"remaining_time":1.951012043},
{"learn":[0.02056968394],"iteration":213,"passed_time":1.997686076,"remaining_time":1.941676186},
{"learn":[0.02047103844],"iteration":214,"passed_time":2.006892745,"remaining_time":1.932217666},
{"learn":[0.02037525547],"iteration":215,"passed_time":2.016130924,"remaining_time":1.92279153},
{"learn":[0.02026704946],"iteration":216,"passed_time":2.024789325,"remaining_time":1.912819409},
{"learn":[0.02013990263],"iteration":217,"passed_time":2.033648638,"remaining_time":1.903047349},
{"learn":[0.02001002611],"iteration":218,"passed_time":2.042721416,"remaining_time":1.893481496},
{"learn":[0.01986308537],"iteration":219,"passed_time":2.051888794,"remaining_time":1.884006983},
{"learn":[0.01976209691],"iteration":220,"passed_time":2.061427936,"remaining_time":1.874873371},
{"learn":[0.01969186041],"iteration":221,"passed_time":2.070907439,"remaining_time":1.865682377},
{"learn":[0.01952301102],"iteration":222,"passed_time":2.080240347,"remaining_time":1.856357978},
{"learn":[0.01942111897],"iteration":223,"passed_time":2.088924816,"remaining_time":1.846460329},
{"learn":[0.0192896866],"iteration":224,"passed_time":2.097571284,"remaining_time":1.836540191},
{"learn":[0.01920988648],"iteration":225,"passed_time":2.106202266,"remaining_time":1.826617895},
{"learn":[0.01912309271],"iteration":226,"passed_time":2.115206303,"remaining_time":1.817027441},
{"learn":[0.01897351955],"iteration":227,"passed_time":2.123737795,"remaining_time":1.807040054},
{"learn":[0.01881855],"iteration":228,"passed_time":2.133035853,"remaining_time":1.797711439},
{"learn":[0.01869707286],"iteration":229,"passed_time":2.14164838,"remaining_time":1.787810822},
{"learn":[0.01858396426],"iteration":230,"passed_time":2.150977997,"remaining_time":1.778514275},
{"learn":[0.01850829151],"iteration":231,"passed_time":2.161133648,"remaining_time":1.769893936},
{"learn":[0.01843471],"iteration":232,"passed_time":2.171367063,"remaining_time":1.761323498},
{"learn":[0.01839406965],"iteration":233,"passed_time":2.180506127,"remaining_time":1.751859624},
{"learn":[0.0183157139],"iteration":234,"passed_time":2.190283257,"remaining_time":1.742906251},
{"learn":[0.0182192468],"iteration":235,"passed_time":2.199678675,"remaining_time":1.733645057},
{"learn":[0.01812465319],"iteration":236,"passed_time":2.208923816,"remaining_time":1.724265426},
{"learn":[0.01803844458],"iteration":237,"passed_time":2.218032185,"remaining_time":1.714781185},
{"learn":[0.01789220284],"iteration":238,"passed_time":2.233549444,"remaining_time":1.710207315},
{"learn":[0.01782200062],"iteration":239,"passed_time":2.24394801,"remaining_time":1.701660574},
{"learn":[0.01764274202],"iteration":240,"passed_time":2.253966359,"remaining_time":1.692812909},
{"learn":[0.01756265893],"iteration":241,"passed_time":2.263850557,"remaining_time":1.683855786},
{"learn":[0.0174499991],"iteration":242,"passed_time":2.273310884,"remaining_time":1.674578799},
{"learn":[0.01735503944],"iteration":243,"passed_time":2.283019038,"remaining_time":1.665481101},
{"learn":[0.01727259858],"iteration":244,"passed_time":2.292943023,"remaining_time":1.656534347},
{"learn":[0.01719229584],"iteration":245,"passed_time":2.303447996,"remaining_time":1.647995314},
{"learn":[0.01708012968],"iteration":246,"passed_time":2.313279698,"remaining_time":1.638963349},
{"learn":[0.01689268328],"iteration":247,"passed_time":2.322574525,"remaining_time":1.629548255},
{"learn":[0.01676131521],"iteration":248,"passed_time":2.331778183,"remaining_time":1.620070786},
{"learn":[0.0166929797],"iteration":249,"passed_time":2.341604493,"remaining_time":1.611023891},
{"learn":[0.01661616606],"iteration":250,"passed_time":2.351594363,"remaining_time":1.602082216},
{"learn":[0.01655748345],"iteration":251,"passed_time":2.361161724,"remaining_time":1.592847195},
{"learn":[0.01647148887],"iteration":252,"passed_time":2.370414027,"remaining_time":1.583399093},
{"learn":[0.01637346274],"iteration":253,"passed_time":2.379678895,"remaining_time":1.573960844},
{"learn":[0.01621433789],"iteration":254,"passed_time":2.389341674,"remaining_time":1.564784548},
{"learn":[0.01610552523],"iteration":255,"passed_time":2.399074326,"remaining_time":1.555649758},
{"learn":[0.01607347986],"iteration":256,"passed_time":2.408371283,"remaining_time":1.54623059},
{"learn":[0.01595374974],"iteration":257,"passed_time":2.417878175,"remaining_time":1.536945816},
{"learn":[0.01588069485],"iteration":258,"passed_time":2.427185435,"remaining_time":1.527533691},
{"learn":[0.01579940312],"iteration":259,"passed_time":2.436825498,"remaining_time":1.518329733},
{"learn":[0.01574829244],"iteration":260,"passed_time":2.446358027,"remaining_time":1.509056101},
{"learn":[0.01569165907],"iteration":261,"passed_time":2.455898589,"remaining_time":1.499785398},
{"learn":[0.01561186532],"iteration":262,"passed_time":2.46546768,"remaining_time":1.49052989},
{"learn":[0.01552180844],"iteration":263,"passed_time":2.475454695,"remaining_time":1.481522128},
{"learn":[0.01546328854],"iteration":264,"passed_time":2.485386112,"remaining_time":1.472474036},
{"learn":[0.01541743549],"iteration":265,"passed_time":2.495259917,"remaining_time":1.463385515},
{"learn":[0.01534533547],"iteration":266,"passed_time":2.504606169,"remaining_time":1.453984855},
{"learn":[0.01529445489],"iteration":267,"passed_time":2.51378619,"remaining_time":1.444489079},
{"learn":[0.01519168556],"iteration":268,"passed_time":2.523096882,"remaining_time":1.435069974},
{"learn":[0.01512424943],"iteration":269,"passed_time":2.532350476,"remaining_time":1.425619527},
{"learn":[0.01509160694],"iteration":270,"passed_time":2.541354368,"remaining_time":1.416031401},
{"learn":[0.01501691593],"iteration":271,"passed_time":2.55117188,"remaining_time":1.406896257},
{"learn":[0.01492074005],"iteration":272,"passed_time":2.560037985,"remaining_time":1.397236849},
{"learn":[0.01484186842],"iteration":273,"passed_time":2.568963718,"remaining_time":1.387615439},
{"learn":[0.01475485496],"iteration":274,"passed_time":2.577925312,"remaining_time":1.378018258},
{"learn":[0.01473051451],"iteration":275,"passed_time":2.587262892,"remaining_time":1.368624573},
{"learn":[0.01468028089],"iteration":276,"passed_time":2.596759451,"remaining_time":1.359314514},
{"learn":[0.01462677294],"iteration":277,"passed_time":2.605629377,"remaining_time":1.349678526},
{"learn":[0.01452297332],"iteration":278,"passed_time":2.61455568,"remaining_time":1.340076926},
{"learn":[0.01446612757],"iteration":279,"passed_time":2.623721347,"remaining_time":1.33060154},
{"learn":[0.01442585565],"iteration":280,"passed_time":2.632738228,"remaining_time":1.321053702},
{"learn":[0.01435708659],"iteration":281,"passed_time":2.641748387,"remaining_time":1.311506292},
{"learn":[0.01429977232],"iteration":282,"passed_time":2.651017776,"remaining_time":1.302090003},
{"learn":[0.01425175432],"iteration":283,"passed_time":2.660122464,"remaining_time":1.292594719},
{"learn":[0.01417755642],"iteration":284,"passed_time":2.669622284,"remaining_time":1.283292115},
{"learn":[0.01410788351],"iteration":285,"passed_time":2.678975729,"remaining_time":1.273918528},
{"learn":[0.0140751338],"iteration":286,"passed_time":2.688069263,"remaining_time":1.264422824},
{"learn":[0.01401235974],"iteration":287,"passed_time":2.697226178,"remaining_time":1.254959402},
{"learn":[0.01394517194],"iteration":288,"passed_time":2.706119181,"remaining_time":1.245376647},
{"learn":[0.01389392381],"iteration":289,"passed_time":2.715185807,"remaining_time":1.235877678},
{"learn":[0.01384377178],"iteration":290,"passed_time":2.724025314,"remaining_time":1.226279437},
{"learn":[0.01380251838],"iteration":291,"passed_time":2.732712224,"remaining_time":1.216618456},
{"learn":[0.01374018631],"iteration":292,"passed_time":2.741151417,"remaining_time":1.206855061},
{"learn":[0.01365650566],"iteration":293,"passed_time":2.750451966,"remaining_time":1.197475686},
{"learn":[0.01361402434],"iteration":294,"passed_time":2.761554718,"remaining_time":1.188872709},
{"learn":[0.01350051299],"iteration":295,"passed_time":2.771950293,"remaining_time":1.179951814},
{"learn":[0.01342723184],"iteration":296,"passed_time":2.781975984,"remaining_time":1.170865313},
{"learn":[0.01337977785],"iteration":297,"passed_time":2.791976577,"remaining_time":1.161762066},
{"learn":[0.01333643696],"iteration":298,"passed_time":2.801813211,"remaining_time":1.152585368},
{"learn":[0.01327737853],"iteration":299,"passed_time":2.810968564,"remaining_time":1.143127216},
{"learn":[0.01321774427],"iteration":300,"passed_time":2.820545168,"remaining_time":1.133840416},
{"learn":[0.01317225149],"iteration":301,"passed_time":2.829919078,"remaining_time":1.124471157},
{"learn":[0.01313148208],"iteration":302,"passed_time":2.838915793,"remaining_time":1.114953727},
{"learn":[0.01308398463],"iteration":303,"passed_time":2.847923912,"remaining_time":1.10544415},
{"learn":[0.01302022314],"iteration":304,"passed_time":2.857167013,"remaining_time":1.096028002},
{"learn":[0.01298285037],"iteration":305,"passed_time":2.866249474,"remaining_time":1.086552088},
{"learn":[0.01293465001],"iteration":306,"passed_time":2.875788426,"remaining_time":1.077249736},
{"learn":[0.01289323965],"iteration":307,"passed_time":2.885163037,"remaining_time":1.06788502},
{"learn":[0.012821767],"iteration":308,"passed_time":2.894174746,"remaining_time":1.058387529},
{"learn":[0.01275473432],"iteration":309,"passed_time":2.902988555,"remaining_time":1.048821672},
{"learn":[0.01271380667],"iteration":310,"passed_time":2.911798083,"remaining_time":1.039259123},
{"learn":[0.01264812091],"iteration":311,"passed_time":2.920268196,"remaining_time":1.029581736},
{"learn":[0.01261456312],"iteration":312,"passed_time":2.928572328,"remaining_time":1.019854261},
{"learn":[0.01257212244],"iteration":313,"passed_time":2.937079562,"remaining_time":1.010205709},
{"learn":[0.01252198041],"iteration":314,"passed_time":2.945911507,"remaining_time":1.000674702},
{"learn":[0.01246795831],"iteration":315,"passed_time":2.955002621,"remaining_time":0.9912350563},
{"learn":[0.01240919541],"iteration":316,"passed_time":2.964271089,"remaining_time":0.9818563545},
{"learn":[0.01236998343],"iteration":317,"passed_time":2.973207916,"remaining_time":0.9723698844},
{"learn":[0.01232453766],"iteration":318,"passed_time":2.982107541,"remaining_time":0.9628748487},
{"learn":[0.0122601128],"iteration":319,"passed_time":2.991130064,"remaining_time":0.9534227079},
{"learn":[0.01218900748],"iteration":320,"passed_time":2.999476619,"remaining_time":0.9437605562},
{"learn":[0.01217673019],"iteration":321,"passed_time":3.007960256,"remaining_time":0.934149148},
{"learn":[0.01208665607],"iteration":322,"passed_time":3.016742786,"remaining_time":0.9246363337},
{"learn":[0.01201800222],"iteration":323,"passed_time":3.025402097,"remaining_time":0.9150907577},
{"learn":[0.0119957355],"iteration":324,"passed_time":3.033841801,"remaining_time":0.9054850913},
{"learn":[0.01196136212],"iteration":325,"passed_time":3.042699323,"remaining_time":0.8960096166},
{"learn":[0.01193077749],"iteration":326,"passed_time":3.051552434,"remaining_time":0.8865366398},
{"learn":[0.01189608931],"iteration":327,"passed_time":3.060114185,"remaining_time":0.8769839433},
{"learn":[0.01181646107],"iteration":328,"passed_time":3.0691434,"remaining_time":0.867569411},
{"learn":[0.01176164862],"iteration":329,"passed_time":3.078367495,"remaining_time":0.858211544},
{"learn":[0.01172303593],"iteration":330,"passed_time":3.087351566,"remaining_time":0.848788497},
{"learn":[0.01169177394],"iteration":331,"passed_time":3.096207668,"remaining_time":0.8393334039},
{"learn":[0.01166201686],"iteration":332,"passed_time":3.105105492,"remaining_time":0.8298930595},
{"learn":[0.01160524855],"iteration":333,"passed_time":3.11375416,"remaining_time":0.8203903177},
{"learn":[0.01156175729],"iteration":334,"passed_time":3.122141768,"remaining_time":0.8108248771},
{"learn":[0.01154016895],"iteration":335,"passed_time":3.130637899,"remaining_time":0.8012942242},
{"learn":[0.01147194457],"iteration":336,"passed_time":3.138997399,"remaining_time":0.7917352489},
{"learn":[0.01142710518],"iteration":337,"passed_time":3.147818269,"remaining_time":0.7822980315},
{"learn":[0.01140021879],"iteration":338,"passed_time":3.156975514,"remaining_time":0.7729468072},
{"learn":[0.01136949604],"iteration":339,"passed_time":3.166404342,"remaining_time":0.7636622236},
{"learn":[0.01130009275],"iteration":340,"passed_time":3.17557414,"remaining_time":0.7543152649},
{"learn":[0.01124044271],"iteration":341,"passed_time":3.184274754,"remaining_time":0.7448595915},
{"learn":[0.01119939519],"iteration":342,"passed_time":3.193260295,"remaining_time":0.7354739456},
{"learn":[0.01117481351],"iteration":343,"passed_time":3.202799607,"remaining_time":0.72621619},
{"learn":[0.01114448634],"iteration":344,"passed_time":3.211933394,"remaining_time":0.7168662938},
{"learn":[0.01112706813],"iteration":345,"passed_time":3.220891997,"remaining_time":0.7074791671},
{"learn":[0.01106166912],"iteration":346,"passed_time":3.229854052,"remaining_time":0.6980952562},
{"learn":[0.01099680479],"iteration":347,"passed_time":3.238845145,"remaining_time":0.6887199446},
{"learn":[0.0109471776],"iteration":348,"passed_time":3.247997638,"remaining_time":0.6793805948},
{"learn":[0.0109043864],"iteration":349,"passed_time":3.25705092,"remaining_time":0.6700219036},
{"learn":[0.01085046706],"iteration":350,"passed_time":3.266148106,"remaining_time":0.6606738334},
{"learn":[0.01084410771],"iteration":351,"passed_time":3.275058185,"remaining_time":0.6512899799},
{"learn":[0.01081927884],"iteration":352,"passed_time":3.284846943,"remaining_time":0.6420805639},
{"learn":[0.01075573943],"iteration":353,"passed_time":3.294516855,"remaining_time":0.6328450456},
{"learn":[0.01067725731],"iteration":354,"passed_time":3.303954685,"remaining_time":0.6235632787},
{"learn":[0.01062541097],"iteration":355,"passed_time":3.313201077,"remaining_time":0.6142451435},
{"learn":[0.01056424234],"iteration":356,"passed_time":3.322421741,"remaining_time":0.6049227259},
{"learn":[0.01053440958],"iteration":357,"passed_time":3.331349915,"remaining_time":0.5955485881},
{"learn":[0.01049845303],"iteration":358,"passed_time":3.33995618,"remaining_time":0.5861204438},
{"learn":[0.01045736662],"iteration":359,"passed_time":3.34900123,"remaining_time":0.576772434},
{"learn":[0.01041237916],"iteration":360,"passed_time":3.358140068,"remaining_time":0.5674419506},
{"learn":[0.01036468102],"iteration":361,"passed_time":3.368179064,"remaining_time":0.5582617233},
{"learn":[0.01034826408],"iteration":362,"passed_time":3.377169477,"remaining_time":0.5489063337},
{"learn":[0.01033849893],"iteration":363,"passed_time":3.38596511,"remaining_time":0.5395219131},
{"learn":[0.01031041127],"iteration":364,"passed_time":3.395747977,"remaining_time":0.5302948895},
{"learn":[0.01028909162],"iteration":365,"passed_time":3.405100281,"remaining_time":0.5209989501},
{"learn":[0.0102396471],"iteration":366,"passed_time":3.413805096,"remaining_time":0.5116056684},
{"learn":[0.01021076402],"iteration":367,"passed_time":3.425850368,"remaining_time":0.502706304},
{"learn":[0.01018686624],"iteration":368,"passed_time":3.435106563,"remaining_time":0.4933892895},
{"learn":[0.01016181629],"iteration":369,"passed_time":3.444357726,"remaining_time":0.4840718966},
{"learn":[0.01014379038],"iteration":370,"passed_time":3.453348189,"remaining_time":0.4747190233},
{"learn":[0.01010259142],"iteration":371,"passed_time":3.462431501,"remaining_time":0.465380578},
{"learn":[0.01007846429],"iteration":372,"passed_time":3.471594107,"remaining_time":0.4560539175},
{"learn":[0.01003889436],"iteration":373,"passed_time":3.480901397,"remaining_time":0.4467467034},
{"learn":[0.0100024966],"iteration":374,"passed_time":3.490234365,"remaining_time":0.4374427071},
{"learn":[0.009961969927],"iteration":375,"passed_time":3.499284487,"remaining_time":0.4281039532},
{"learn":[0.009925768734],"iteration":376,"passed_time":3.50882897,"remaining_time":0.4188257391},
{"learn":[0.009879567067],"iteration":377,"passed_time":3.519889029,"remaining_time":0.4097225325},
{"learn":[0.009836515802],"iteration":378,"passed_time":3.528945443,"remaining_time":0.4003816729},
{"learn":[0.009805501853],"iteration":379,"passed_time":3.53791768,"remaining_time":0.3910330067},
{"learn":[0.009781425878],"iteration":380,"passed_time":3.546816465,"remaining_time":0.3816784122},
{"learn":[0.009758522788],"iteration":381,"passed_time":3.555886913,"remaining_time":0.3723441793},
{"learn":[0.00972545642],"iteration":382,"passed_time":3.564986929,"remaining_time":0.3630143348},
{"learn":[0.009703839936],"iteration":383,"passed_time":3.575055174,"remaining_time":0.3537815016},
{"learn":[0.009676657641],"iteration":384,"passed_time":3.583984228,"remaining_time":0.3444348479},
{"learn":[0.009637288451],"iteration":385,"passed_time":3.593479506,"remaining_time":0.3351431664},
{"learn":[0.009610088568],"iteration":386,"passed_time":3.603021549,"remaining_time":0.325854662},
{"learn":[0.009562394588],"iteration":387,"passed_time":3.612403442,"remaining_time":0.3165508171},
{"learn":[0.009538060204],"iteration":388,"passed_time":3.621103386,"remaining_time":0.3071887191},
{"learn":[0.009501758226],"iteration":389,"passed_time":3.630032602,"remaining_time":0.2978488289},
{"learn":[0.009474558182],"iteration":390,"passed_time":3.638941428,"remaining_time":0.2885094227},
{"learn":[0.009436908183],"iteration":391,"passed_time":3.64763556,"remaining_time":0.2791557827},
{"learn":[0.009412296242],"iteration":392,"passed_time":3.656938639,"remaining_time":0.2698504339},
{"learn":[0.00938284259],"iteration":393,"passed_time":3.666185951,"remaining_time":0.2605411336},
{"learn":[0.009348751534],"iteration":394,"passed_time":3.675187548,"remaining_time":0.2512153514},
{"learn":[0.009319373721],"iteration":395,"passed_time":3.684657668,"remaining_time":0.2419219681},
{"learn":[0.009301074263],"iteration":396,"passed_time":3.694188437,"remaining_time":0.2326315137},
{"learn":[0.009272684876],"iteration":397,"passed_time":3.703679524,"remaining_time":0.2233374587},
{"learn":[0.009260693706],"iteration":398,"passed_time":3.712681531,"remaining_time":0.2140142236},
{"learn":[0.009226423295],"iteration":399,"passed_time":3.722038707,"remaining_time":0.2047121289},
{"learn":[0.009196291451],"iteration":400,"passed_time":3.730682663,"remaining_time":0.1953724088},
{"learn":[0.009173345941],"iteration":401,"passed_time":3.739595862,"remaining_time":0.1860495454},
{"learn":[0.009148795827],"iteration":402,"passed_time":3.749169025,"remaining_time":0.1767598299},
{"learn":[0.009140542589],"iteration":403,"passed_time":3.758860143,"remaining_time":0.1674739668},
{"learn":[0.00910495764],"iteration":404,"passed_time":3.767966052,"remaining_time":0.158161538},
{"learn":[0.009056389908],"iteration":405,"passed_time":3.777633613,"remaining_time":0.1488722606},
{"learn":[0.009036932619],"iteration":406,"passed_time":3.78767914,"remaining_time":0.1395950543},
{"learn":[0.009012146529],"iteration":407,"passed_time":3.797399818,"remaining_time":0.1303029349},
{"learn":[0.008957303531],"iteration":408,"passed_time":3.807392769,"remaining_time":0.1210173741},
{"learn":[0.008918178641],"iteration":409,"passed_time":3.8175474,"remaining_time":0.1117330946},
{"learn":[0.008886706513],"iteration":410,"passed_time":3.827367148,"remaining_time":0.1024356171},
{"learn":[0.008864977522],"iteration":411,"passed_time":3.836849342,"remaining_time":0.09312741121},
{"learn":[0.008836174449],"iteration":412,"passed_time":3.845587147,"remaining_time":0.08380214122},
{"learn":[0.008823586836],"iteration":413,"passed_time":3.854768239,"remaining_time":0.07448827515},
{"learn":[0.008784804405],"iteration":414,"passed_time":3.863852521,"remaining_time":0.06517341601},
{"learn":[0.008756140509],"iteration":415,"passed_time":3.873436946,"remaining_time":0.05586687903},
{"learn":[0.008738191312],"iteration":416,"passed_time":3.882760792,"remaining_time":0.04655588479},
{"learn":[0.008721941457],"iteration":417,"passed_time":3.893130489,"remaining_time":0.03725483721},
{"learn":[0.008709962181],"iteration":418,"passed_time":3.903182678,"remaining_time":0.02794641536},
{"learn":[0.008693861572],"iteration":419,"passed_time":3.915886072,"remaining_time":0.01864707653},
{"learn":[0.008677326542],"iteration":420,"passed_time":3.925326214,"remaining_time":0.009323815234},
{"learn":[0.008661290605],"iteration":421,"passed_time":3.934415147,"remaining_time":0}
]}